fil_io/__init__.py
fil_io/csv.py
fil_io/json.py
fil_io/select.py
fil_io/xls.py
fil_io/xml.py
fil_io-0.1.3.dist-info/LICENSE
fil_io-0.1.3.dist-info/METADATA
fil_io-0.1.3.dist-info/WHEEL
fil_io-0.1.3.dist-info/top_level.txt
fil_io-0.1.3.dist-info/RECORD
